template_config_model/config_model.py
template_config_model/jsonld/config_model.context.jsonld
template_config_model/jsonld/config_model.model.context.jsonld
template_config_model/jsonschema/config_model.schema.json
template_config_model/model/schema/config_model.yaml
template_config_model/schema/config_model.yaml
template_config_model-0.0.3.data/data/template_config_model/jsonschema/config_model.schema.json
template_config_model-0.0.3.data/data/template_config_model/model/schema/config_model.yaml
template_config_model-0.0.3.data/data/template_config_model/schema/config_model.yaml
template_config_model-0.0.3.dist-info/AUTHORS
template_config_model-0.0.3.dist-info/METADATA
template_config_model-0.0.3.dist-info/WHEEL
template_config_model-0.0.3.dist-info/pbr.json
template_config_model-0.0.3.dist-info/top_level.txt
template_config_model-0.0.3.dist-info/RECORD
