Metadata-Version: 2.1
Name: template-config-model
Version: 0.0.3
Summary: Configuration parameters for LinkML model generation
Home-page: https://linkml.github.io/template_config_model
Author: Harold Solbrig
Author-email: solbrig@jhu.edu
License: CC0 1.0 Universal
Keywords: linkml,LOD,Modeling,Linked open data,model
Platform: UNKNOWN
Classifier: Development Status :: 4 - Beta
Classifier: Environment :: Console
Classifier: Intended Audience :: Developers
Classifier: Intended Audience :: Science/Research
Classifier: Intended Audience :: Information Technology
Classifier: License :: CC0 1.0 Universal (CC0 1.0) Public Domain Dedication
Classifier: Programming Language :: Python :: 3 :: Only
Classifier: Programming Language :: Python :: 3.7
Classifier: Programming Language :: Python :: 3.8
Classifier: Programming Language :: Python :: 3.9
Requires-Python: >=3.7
Requires-Dist: linkml-model (>=0.1.0.dev1)
Requires-Dist: linkml-runtime (>=0.1.6)
